MANIFEST.in
README.rst
constraints.txt
constraints_plone43.txt
constraints_plone50.txt
constraints_plone51.txt
constraints_plone52.txt
requirements.txt
setup.cfg
setup.py
docs/HISTORY.rst
docs/INSTALL.txt
docs/LICENSE.GPL
docs/LICENSE.txt
rt/__init__.py
rt.lastmodifier.egg-info/PKG-INFO
rt.lastmodifier.egg-info/SOURCES.txt
rt.lastmodifier.egg-info/dependency_links.txt
rt.lastmodifier.egg-info/entry_points.txt
rt.lastmodifier.egg-info/namespace_packages.txt
rt.lastmodifier.egg-info/not-zip-safe
rt.lastmodifier.egg-info/requires.txt
rt.lastmodifier.egg-info/top_level.txt
rt/lastmodifier/__init__.py
rt/lastmodifier/configure.zcml
rt/lastmodifier/extender.py
rt/lastmodifier/indexer.py
rt/lastmodifier/interfaces.py
rt/lastmodifier/patches.py
rt/lastmodifier/patches.zcml
rt/lastmodifier/permissions.py
rt/lastmodifier/permissions.zcml
rt/lastmodifier/profiles.zcml
rt/lastmodifier/setuphandlers.py
rt/lastmodifier/testing.py
rt/lastmodifier/upgrades.py
rt/lastmodifier/upgrades.zcml
rt/lastmodifier/Extensions/install.py
rt/lastmodifier/browser/__init__.py
rt/lastmodifier/browser/changenote.py
rt/lastmodifier/browser/configure.zcml
rt/lastmodifier/browser/document_byline.pt
rt/lastmodifier/browser/document_byline.py
rt/lastmodifier/browser/lastmodifier.py
rt/lastmodifier/browser/security.py
rt/lastmodifier/browser/site.py
rt/lastmodifier/browser/versioning_edit.pt
rt/lastmodifier/locales/rebuildPo.sh
rt/lastmodifier/locales/rt.lastmodifier-manual.pot
rt/lastmodifier/locales/rt.lastmodifier.pot
rt/lastmodifier/locales/it/LC_MESSAGES/rt.lastmodifier.po
rt/lastmodifier/profiles/default/browserlayer.xml
rt/lastmodifier/profiles/default/catalog.xml
rt/lastmodifier/profiles/default/metadata.xml
rt/lastmodifier/profiles/default/portal_atct.xml
rt/lastmodifier/profiles/default/rolemap.xml
rt/lastmodifier/profiles/default/rt.lastmodifier_various.txt
rt/lastmodifier/profiles/new-collection/registry.xml
rt/lastmodifier/profiles/new-collection-uninstall/registry.xml
rt/lastmodifier/profiles/to_1100/rolemap.xml
rt/lastmodifier/profiles/to_1110/rolemap.xml
rt/lastmodifier/profiles/uninstall/browserlayer.xml
rt/lastmodifier/profiles/uninstall/catalog.xml
rt/lastmodifier/profiles/uninstall/portal_atct.xml
rt/lastmodifier/tests/__init__.py
rt/lastmodifier/tests/base.py
