Metadata-Version: 2.1
Name: rt.lastmodifier
Version: 1.1.2
Summary: Extends features and shown data in Plone document byline section
Home-page: https://github.com/redturtle/rt.lastmodifier
Author: RedTurtle Technology
Author-email: sviluppoplone@redturtle.it
License: GPL version 2
Project-URL: PyPI, https://pypi.python.org/pypi/rt.lastmodifier
Project-URL: Source, https://github.com/redturtle/rt.lastmodifier
Project-URL: Tracker, https://github.com/redturtle/rt.lastmodifier/issues
Keywords: Python Plone
Platform: UNKNOWN
Classifier: Environment :: Web Environment
Classifier: Framework :: Plone
Classifier: Framework :: Plone :: Addon
Classifier: Framework :: Plone :: 4.3
Classifier: Framework :: Plone :: 5.1
Classifier: Framework :: Plone :: 5.2
Classifier: Programming Language :: Python
Classifier: Programming Language :: Python :: 2.7
Classifier: Programming Language :: Python :: 3.6
Classifier: Programming Language :: Python :: 3.7
Classifier: Operating System :: OS Independent
Classifier: License :: OSI Approved :: GNU General Public License v2 (GPLv2)
Requires-Python: >=3.6
Provides-Extra: test
